flowgl/__init__.py
flowgl/client.py
flowgl-0.1.4.post1.dist-info/WHEEL
flowgl-0.1.4.post1.dist-info/METADATA
flowgl-0.1.4.post1.dist-info/RECORD
