Metadata-Version: 2.1
Name: flowgl
Version: 0.1.4.post1
Summary: Flow Immersive python client for datasets API
Author: Flow Immersive
Author-email: info@flow.gl
Requires-Python: >=3.8,<4.0
Classifier: Programming Language :: Python :: 3
Classifier: Programming Language :: Python :: 3.8
Classifier: Programming Language :: Python :: 3.9
Classifier: Programming Language :: Python :: 3.10
Classifier: Programming Language :: Python :: 3.11
Requires-Dist: jsonpath-ng (>=1.5.3,<2.0.0)
Requires-Dist: requests-toolbelt (>=0.10.1,<0.11.0)
